setup.py
stitch_orchestrator.py
stitch_orchestrator/logging.conf
stitch_orchestrator.egg-info/PKG-INFO
stitch_orchestrator.egg-info/SOURCES.txt
stitch_orchestrator.egg-info/dependency_links.txt
stitch_orchestrator.egg-info/entry_points.txt
stitch_orchestrator.egg-info/requires.txt
stitch_orchestrator.egg-info/top_level.txt